{
"@fastfood": "Fast food",
"cuisine-bagel": "Chiflă",
"cuisine-breakfast": "Mic dejun",
"cuisine-burger|@fastfood": "Burger",
"cuisine-cake": "Tort",
"cuisine-coffee_shop": "Cafea",
"cuisine-curry": "Curry",
"cuisine-diner": "Cină",
"cuisine-donut": "Gogoașă",
"cuisine-fish_and_chips": "Restaurant fish and chips",
"cuisine-friture|@fastfood": "Prăjit",
"cuisine-grill": "Grătar",
"cuisine-hotdog|@fastfood": "Hot dog",
"cuisine-ice_cream": "Înghețată",
"cuisine-kebab|@fastfood": "Kebab",
"cuisine-noodles": "Tăiței",
"cuisine-pancake|cuisine-crepe": "Clătită|Crep",
"cuisine-pasta": "Paste",
"cuisine-pizza|@fastfood": "Pizza",
"cuisine-ramen": "Ramen",
"cuisine-sandwich|@fastfood": "Sandwich",
"cuisine-sausage|@fastfood": "Cârnat",
"cuisine-seafood|cuisine-fish": "Fructe de mare|Pește",
"cuisine-soba": "Soba",
"cuisine-steak_house": "Restaurant steakhouse",
"cuisine-sushi": "Sushi",
"cuisine-tapas": "Tapas",
"cuisine-tea": "Ceai",
"cuisine-vegetarian": "Bucătărie vegetarian",
"cuisine-vegan": "Bucătărie vegan|Bucătărie vegetarian"
}